youtube/Add_ons.py
youtube/Cipher.py
youtube/Cli.py
youtube/Config.py
youtube/Connection.py
youtube/Downloader.py
youtube/Error.py
youtube/Extract.py
youtube/Stream.py
youtube/__init__.py
youtube/__main__.py
youtube.py-2.1.0.dist-info/LICENSE
youtube.py-2.1.0.dist-info/METADATA
youtube.py-2.1.0.dist-info/WHEEL
youtube.py-2.1.0.dist-info/entry_points.txt
youtube.py-2.1.0.dist-info/top_level.txt
youtube.py-2.1.0.dist-info/RECORD
