Metadata-Version: 2.1
Name: youtube.py
Version: 2.1.0
Summary: YouTube.py is a light python module for youtube.
Home-page: https://youtube-python.mayankfawkes.xyz/
Author: Mayank Gupta
Author-email: mayankfawkes@gmail.com
License: MIT License
Project-URL: Documentation, https://youtube-python.readthedocs.io
Project-URL: Source, https://github.com/youtube-py/youtube.py
Keywords: Youtube,youtube.py,Youtube Python,Python Youtube,Youtube downloader,Youtube Videos
Platform: UNKNOWN
Classifier: Topic :: Software Development :: Libraries :: Python Modules
Classifier: Programming Language :: Python :: Implementation
Classifier: Programming Language :: Python :: 3 :: Only
Classifier: Programming Language :: Python :: 3
Classifier: Programming Language :: Python :: 3.6
Classifier: Programming Language :: Python :: 3.7
Classifier: Programming Language :: Python :: 3.8
Classifier: Programming Language :: Python :: 3.9
Classifier: License :: OSI Approved :: MIT License
Classifier: Development Status :: 5 - Production/Stable
Classifier: Topic :: System :: Networking
Classifier: Topic :: Internet :: WWW/HTTP
Classifier: Topic :: Multimedia :: Video
Classifier: Natural Language :: English
Classifier: Environment :: Plugins
Classifier: Environment :: Console
Classifier: Topic :: Terminals
Classifier: Topic :: Utilities
Requires-Python: >=3.6
Requires-Dist: requests
